traceai_groq/__init__.py
traceai_groq/_request_attributes_extractor.py
traceai_groq/_response_attributes_extractor.py
traceai_groq/_utils.py
traceai_groq/_with_span.py
traceai_groq/_wrappers.py
traceai_groq/version.py
traceai_groq-0.1.8.dist-info/METADATA
traceai_groq-0.1.8.dist-info/WHEEL
traceai_groq-0.1.8.dist-info/RECORD
