Metadata-Version: 2.3
Name: traceAI-groq
Version: 0.1.8
Summary: OpenTelemetry instrumentation for Groq
Author: Future AGI
Author-email: no-reply@futureagi.com
Requires-Python: >=3.10,<3.13
Classifier: Programming Language :: Python :: 3
Classifier: Programming Language :: Python :: 3.10
Classifier: Programming Language :: Python :: 3.11
Classifier: Programming Language :: Python :: 3.12
Requires-Dist: fi-instrumentation-otel (>=0.1.11)
Requires-Dist: groq (>=0.9.0)
